tfc_utils/__init__.py
tfc_utils/__main__.py
tfc_utils/cli.py
tfc_utils/terraform_cloud.py
tfc_utils-0.0.4.dist-info/WHEEL
tfc_utils-0.0.4.dist-info/METADATA
tfc_utils-0.0.4.dist-info/RECORD
