Metadata-Version: 2.1
Name: tfc-utils
Version: 0.0.4
Summary: A helper tool (CLI) for Terraform Cloud
Author: Ilya Sotkov
Author-email: ilya@sotkov.com
Requires-Python: >=3.8,<4.0
Classifier: Programming Language :: Python :: 3
Classifier: Programming Language :: Python :: 3.10
Classifier: Programming Language :: Python :: 3.8
Classifier: Programming Language :: Python :: 3.9
Requires-Dist: terrasnek
Requires-Dist: typer
